azure/ai/vision/Azure-AI-Vision-Extension-Image.dll
azure/ai/vision/Azure-AI-Vision-Input-Device.dll
azure/ai/vision/Azure-AI-Vision-Input-File.dll
azure/ai/vision/Azure-AI-Vision-Native.dll
azure/ai/vision/Vision_Core.dll
azure/ai/vision/Vision_Media.dll
azure/ai/vision/Vision_Media_VideoIngester.dll
azure/ai/vision/__init__.py
azure/ai/vision/enums.py
azure/ai/vision/image_analysis_client.py
azure/ai/vision/image_analysis_data.py
azure/ai/vision/interop.py
azure/ai/vision/jpeg62.dll
azure/ai/vision/properties.py
azure/ai/vision/turbojpeg.dll
azure/ai/vision/version.py
azure/ai/vision/vision_base_client.py
azure_ai_vision-0.11.0.dist-info/LICENSE.md
azure_ai_vision-0.11.0.dist-info/METADATA
azure_ai_vision-0.11.0.dist-info/REDIST.txt
azure_ai_vision-0.11.0.dist-info/ThirdPartyNotices.txt
azure_ai_vision-0.11.0.dist-info/WHEEL
azure_ai_vision-0.11.0.dist-info/top_level.txt
azure_ai_vision-0.11.0.dist-info/RECORD
