Metadata-Version: 2.1
Name: azure-ai-vision
Version: 0.11.0
Summary: Microsoft Azure AI Vision SDK for Python
Author: Microsoft
Classifier: Development Status :: 4 - Beta
Classifier: Intended Audience :: Developers
Classifier: License :: Other/Proprietary License
Classifier: Operating System :: POSIX :: Linux
Classifier: Operating System :: MacOS :: MacOS X
Classifier: Operating System :: Microsoft :: Windows
Classifier: Programming Language :: Python
Classifier: Topic :: Scientific/Engineering
Classifier: Topic :: Software Development :: Libraries :: Python Modules
Requires-Python: >=3.7
License-File: licensefiles/vision/REDIST.txt
License-File: licensefiles/vision/ThirdPartyNotices.txt
License-File: licensefiles/vision/LICENSE.md
